visier_api_core/__init__.py
visier_api_core/api_client.py
visier_api_core/api_response.py
visier_api_core/configuration.py
visier_api_core/exceptions.py
visier_api_core/py.typed
visier_api_core/rest.py
visier_api_core-22222222.99201.1906.dist-info/METADATA
visier_api_core-22222222.99201.1906.dist-info/WHEEL
visier_api_core-22222222.99201.1906.dist-info/top_level.txt
visier_api_core-22222222.99201.1906.dist-info/RECORD
