Metadata-Version: 2.4
Name: visier-api-core
Version: 22222222.99201.1906
Summary: Visier Authentication APIs
Home-page: 
Author: Visier
Author-email: alpine@visier.com
License: Apache License, Version 2.0
Keywords: Visier,Visier-SDK,Visier Authentication APIs
Requires-Dist: urllib3<3.0.0,>=1.25.3
Requires-Dist: python-dateutil
Requires-Dist: Flask>=3.0.0
Requires-Dist: pydantic>=2
Requires-Dist: typing-extensions>=4.7.1
Dynamic: author
Dynamic: author-email
Dynamic: description
Dynamic: description-content-type
Dynamic: keywords
Dynamic: license
Dynamic: requires-dist
Dynamic: summary
